{"cameraMode":{"drawMode":0,"name":"Shaded","section":"Shading Mode"},"sceneLighting":true,"audioPlay":false,"sceneViewState":{"m_AlwaysRefresh":true,"showFog":true,"showSkybox":true,"showFlares":true,"showImageEffects":true,"showParticleSystems":true,"showVisualEffectGraphs":true,"m_FxEnabled":true},"in2DMode":false,"pivot":{"x":-1.25520920753479,"y":10.589874267578125,"z":-73.0704574584961},"rotation":{"x":0.44390958547592165,"y":-0.1070709377527237,"z":0.053583744913339618,"w":0.8881660103797913},"size":1.7320507764816285,"orthographic":false}